{
  "bosses": [
    {
      "id": 1,
      "name": "Bell Beast",
      "location": "The Marrow",
      "health": 150,
      "phases": 2,
      "image": "../images/Bosses/bellbeast.png"
    },
    {
      "id": 2,
      "name": "Bell Eater",
      "location": "Any Bellway (Act 3)",
      "health": 800,
      "phases": 2,
      "image": "../images/Bosses/belleater.png"
    },
    {
      "id": 3,
      "name": "Broodmother",
      "location": "The Slab",
      "health": 700,
      "phases": 2,
      "image": "../images/Bosses/broodmother.png"
    },
    {
      "id": 4,
      "name": "Cogwork Dancers",
      "location": "Cogwork Core",
      "health": 630,
      "phases": 4,
      "image": "../images/Bosses/cogworkdancers.png"
    },
    {
      "id": 5,
      "name": "Crawfather",
      "location": "Craw Lake",
      "health": 1300,
      "phases": 1,
      "image": "../images/Bosses/crawfather.png"
    },
    {
      "id": 6,
      "name": "Crust King Khann",
      "location": "Coral Tower",
      "health": 1650,
      "phases": 1,
      "image": "../images/Bosses/crustkingkhann.png"
    },
    {
      "id": 7,
      "name": "Disgraced Chef Lugoli",
      "location": "Sinner's Road",
      "health": 600,
      "phases": 2,
      "image": "../images/Bosses/disgracedcheflugoli.png"
    },
    {
      "id": 8,
      "name": "Father of the Flame",
      "location": "Wisp Thicket",
      "health": 640,
      "phases": 2,
      "image": "../images/Bosses/fatheroftheflame.png"
    },
    {
      "id": 9,
      "name": "First Sinner",
      "location": "The Slab",
      "health": 1300,
      "phases": 2,
      "image": "../images/Bosses/firstsinner.png"
    },
    {
      "id": 10,
      "name": "Forebrothers Signis and Gron",
      "location": "Deep Docks",
      "health": 1240,
      "phases": 3,
      "image": "../images/Bosses/forebrotherssignisandgron.png"
    },
    {
      "id": 11,
      "name": "Fourth Chorus",
      "location": "Far Fields",
      "health": 500,
      "phases": 4,
      "image": "../images/Bosses/fourthchorus.png"
    },
    {
      "id": 12,
      "name": "Garmond and Zaza",
      "location": "Greymoor, Sinner's Road, Choral Chambers, Whispering Vaults, High Halls",
      "health": 460,
      "phases": 1,
      "image": "../images/Bosses/garmondandzaza.png"
    },
    {
      "id": 13,
      "name": "Grandmother Silk",
      "location": "The Cradle",
      "health": 1095,
      "phases": 6,
      "image": "../images/Bosses/grandmothersilk.png"
    },
    {
      "id": 14,
      "name": "Great Conchflies",
      "location": "Blasted Steps",
      "health": 400,
      "phases": 1,
      "image": "../images/Bosses/greatconchflies.png"
    },
    {
      "id": 15,
      "name": "Groal the Great",
      "location": "Bilewater",
      "health": 650,
      "phases": 2,
      "image": "../images/Bosses/groalthegreat.png"
    },
    {
      "id": 16,
      "name": "Gurr the Outcast",
      "location": "Far Fields",
      "health": 1000,
      "phases": 1,
      "image": "../images/Bosses/gurrtheoutcast.png"
    }
  ]
}
